CHANGES.rst
COPYING.LGPLv3
MANIFEST.in
README.rst
setup.py
django_like/__init__.py
django_like/models.py
django_like.egg-info/PKG-INFO
django_like.egg-info/SOURCES.txt
django_like.egg-info/dependency_links.txt
django_like.egg-info/not-zip-safe
django_like.egg-info/top_level.txt
django_like/management/__init__.py
django_like/management/commands/__init__.py
django_like/management/commands/benchmark_like.py