Metadata-Version: 1.1
Name: django-like
Version: 0.1.0
Summary: Django application that provider the like and ilike lookups for the querysets
Home-page: https://github.com/goinnn/django-like
Author: Pablo Martin
Author-email: goinnn@gmail.com
License: LGPL 3
Keywords: django,querysets,lookup,like,ilike
Platform: UNKNOWN
Classifier: Development Status :: 4 - Beta
Classifier: Framework :: Django
Classifier: License :: OSI Approved :: GNU Library or Lesser General Public License (LGPL)
Classifier: Programming Language :: Python :: 2
Classifier: Programming Language :: Python :: 3
